CHANGELOG.md
django_q/__init__.py
django_q/admin.py
django_q/apps.py
django_q/brokers/__init__.py
django_q/brokers/aws_sqs.py
django_q/brokers/disque.py
django_q/brokers/ironmq.py
django_q/brokers/mongo.py
django_q/brokers/orm.py
django_q/brokers/redis_broker.py
django_q/cluster.py
django_q/conf.py
django_q/core_signing.py
django_q/humanhash.py
django_q/locale/de/LC_MESSAGES/django.mo
django_q/locale/de/LC_MESSAGES/django.po
django_q/locale/fr/LC_MESSAGES/django.mo
django_q/locale/fr/LC_MESSAGES/django.po
django_q/management/__init__.py
django_q/management/commands/__init__.py
django_q/management/commands/qcluster.py
django_q/management/commands/qinfo.py
django_q/management/commands/qmemory.py
django_q/management/commands/qmonitor.py
django_q/migrations/0001_initial.py
django_q/migrations/0002_auto_20150630_1624.py
django_q/migrations/0003_auto_20150708_1326.py
django_q/migrations/0004_auto_20150710_1043.py
django_q/migrations/0005_auto_20150718_1506.py
django_q/migrations/0006_auto_20150805_1817.py
django_q/migrations/0007_ormq.py
django_q/migrations/0008_auto_20160224_1026.py
django_q/migrations/0009_auto_20171009_0915.py
django_q/migrations/0010_auto_20200610_0856.py
django_q/migrations/0011_auto_20200628_1055.py
django_q/migrations/0012_auto_20200702_1608.py
django_q/migrations/0013_task_attempt_count.py
django_q/migrations/0014_schedule_cluster.py
django_q/migrations/__init__.py
django_q/models.py
django_q/monitor.py
django_q/queues.py
django_q/signals.py
django_q/signing.py
django_q/status.py
django_q/tasks.py
django_q/tests/__init__.py
django_q/tests/settings.py
django_q/tests/tasks.py
django_q/tests/test_admin.py
django_q/tests/test_brokers.py
django_q/tests/test_cached.py
django_q/tests/test_cluster.py
django_q/tests/test_commands.py
django_q/tests/test_monitor.py
django_q/tests/test_scheduler.py
django_q/tests/testing_utilities/__init__.py
django_q/tests/testing_utilities/multiple_database_routers.py
django_q/tests/urls.py
django_q-1.3.8.dist-info/entry_points.txt
django_q-1.3.8.dist-info/LICENSE
django_q-1.3.8.dist-info/WHEEL
django_q-1.3.8.dist-info/METADATA
django_q-1.3.8.dist-info/RECORD
